pytyu/__init__.py
pytyu/json.py
pytyu/json_schema.py
pytyu/py.typed
pytyu-0.0.6.dist-info/LICENSE
pytyu-0.0.6.dist-info/METADATA
pytyu-0.0.6.dist-info/WHEEL
pytyu-0.0.6.dist-info/top_level.txt
pytyu-0.0.6.dist-info/RECORD
