Metadata-Version: 2.1
Name: pytyu
Version: 0.0.6
Summary: Utilities to help with types and type checking.
Author-email: Narvin Singh <Narvin.A.Singh@gmail.com>
License: The MIT License (MIT)
Project-URL: Homepage, https://gitlab.com/narvin/pytyu
Project-URL: Repository, https://gitlab.com/narvin/pytyu
Project-URL: Bug Tracker, https://gitlab.com/narvin/pytyu/-/issues
Keywords: type checker,type checking,type utility
Classifier: Programming Language :: Python :: 3
Classifier: License :: OSI Approved :: MIT License
Classifier: Operating System :: OS Independent
Requires-Python: >=3.10
License-File: LICENSE
Provides-Extra: code_quality
Requires-Dist: black (>=22.10.0) ; extra == 'code_quality'
Requires-Dist: mypy (>=0.991) ; extra == 'code_quality'
Requires-Dist: pycodestyle (>=2.9.1) ; extra == 'code_quality'
Requires-Dist: pylint (>=2.15.5) ; extra == 'code_quality'
Provides-Extra: deploy
Requires-Dist: build (>=0.7.0) ; extra == 'deploy'
Requires-Dist: twine (>=4.0.0) ; extra == 'deploy'
Provides-Extra: docs
Requires-Dist: sphinx (>=5.3.0) ; extra == 'docs'
Provides-Extra: test
Requires-Dist: pytest (>=7.2.0) ; extra == 'test'
Requires-Dist: pytest-xdist (>=2.5.0) ; extra == 'test'
